AzureAuthenticate/AzureAuthenticator.py
AzureAuthenticate/__init__.py
AzureKeyValut/AzureKeyVault.py
AzureKeyValut/__init__.py
AzureResourceManger/AzureResourceManager.py
AzureResourceManger/__init__.py
AzureStorage/AzureBlobStorage.py
AzureStorage/__init__.py
AzurePythonConnectors-1.0.0.dist-info/LICENSE
AzurePythonConnectors-1.0.0.dist-info/METADATA
AzurePythonConnectors-1.0.0.dist-info/WHEEL
AzurePythonConnectors-1.0.0.dist-info/top_level.txt
AzurePythonConnectors-1.0.0.dist-info/RECORD
